shadetree/__init__.py
shadetree/elm327.py
shadetree/obd/__init__.py
shadetree/obd/commands.py
shadetree/obd/fuel_type.py
shadetree/obd/modes.py
shadetree/obd/pids.py
shadetree/obd/scanner.py
shadetree-0.1.data/scripts/shadetree
shadetree-0.1.dist-info/DESCRIPTION.rst
shadetree-0.1.dist-info/METADATA
shadetree-0.1.dist-info/metadata.json
shadetree-0.1.dist-info/RECORD
shadetree-0.1.dist-info/top_level.txt
shadetree-0.1.dist-info/WHEEL
