Metadata-Version: 2.0
Name: shadetree
Version: 0.1
Summary: ShadeTree OBD
Home-page: http://hub-ology.org
Author: HUB-OLOGY
Author-email: corbinbs@hubology.org
License: MIT
Download-URL: https://github.com/corbinbs/shadetree/tarball/0.1
Keywords: obd,obdii,automotive
Platform: any
Classifier: Development Status :: 3 - Alpha
Classifier: Environment :: Web Environment
Classifier: Intended Audience :: Developers
Classifier: Intended Audience :: Education
Classifier: License :: OSI Approved :: MIT License
Classifier: Operating System :: OS Independent
Classifier: Programming Language :: Python
Classifier: Programming Language :: Python :: 2.7
Classifier: Programming Language :: Python :: 3.4
Classifier: Programming Language :: Python :: Implementation :: PyPy
Classifier: Topic :: Communications
Classifier: Topic :: Scientific/Engineering :: Information Analysis
Classifier: Topic :: Software Development :: Libraries :: Python Modules
Classifier: Topic :: System :: Logging
Classifier: Topic :: Utilities
Requires-Dist: pyserial (>=2.7)
